src/__init__.py
src/cli.py
src/indicators.py
indicators_cli-1.2.9.dist-info/METADATA
indicators_cli-1.2.9.dist-info/WHEEL
indicators_cli-1.2.9.dist-info/entry_points.txt
indicators_cli-1.2.9.dist-info/top_level.txt
indicators_cli-1.2.9.dist-info/RECORD
