Metadata-Version: 2.4
Name: indicators-cli
Version: 1.2.9
Summary: CLI tool to calculate stock indicators
Home-page: https://github.com/ibitec7/indicators-cli
Author: Syed Ibrahim Omer
Author-email: syed.ibrahim.omer.2@gmail.com
Classifier: Programming Language :: Python :: 3
Classifier: License :: OSI Approved :: MIT License
Classifier: Operating System :: OS Independent
Requires-Python: >=3.6
Requires-Dist: polars
Requires-Dist: numpy
Requires-Dist: yfinance
Requires-Dist: click
Dynamic: author
Dynamic: author-email
Dynamic: classifier
Dynamic: description
Dynamic: description-content-type
Dynamic: home-page
Dynamic: requires-dist
Dynamic: requires-python
Dynamic: summary
